timemachines/__init__.py
timemachines/skating.py
timemachines/inclusion/__init__.py
timemachines/inclusion/humpdayinclusion.py
timemachines/inclusion/matplotlibinclusion.py
timemachines/inclusion/micropredictioninclusion.py
timemachines/inclusion/pandasinclusion.py
timemachines/inclusion/scipyinclusion.py
timemachines/inclusion/sklearninclusion.py
timemachines/inclusion/statsmodelsinclusion.py
timemachines/inclusion/threezainclusion.py
timemachines/skaters/__init__.py
timemachines/skaters/allskaters.py
timemachines/skaters/localskaters.py
timemachines/skaters/networkedskaters.py
timemachines/skaters/preskaters.py
timemachines/skaters/pypi.py
timemachines/skaters/ats/__init__.py
timemachines/skaters/ats/atsinclusion.py
timemachines/skaters/bats/__init__.py
timemachines/skaters/bats/allbatsskaters.py
timemachines/skaters/bats/batsfactory.py
timemachines/skaters/bats/batsifactory.py
timemachines/skaters/bats/batsinclusion.py
timemachines/skaters/divine/__init__.py
timemachines/skaters/divine/divineinclusion.py
timemachines/skaters/divine/divineparams.py
timemachines/skaters/divine/divineskaterfactory.py
timemachines/skaters/divine/divineskaters.py
timemachines/skaters/dlm/__init__.py
timemachines/skaters/dlm/alldlmskaters.py
timemachines/skaters/dlm/dlmcomposed.py
timemachines/skaters/dlm/dlmexogenous.py
timemachines/skaters/dlm/dlmhacks.py
timemachines/skaters/dlm/dlminclusion.py
timemachines/skaters/dlm/dlmunivariate.py
timemachines/skaters/drts/alldartsskaters.py
timemachines/skaters/drts/dartsarimaskater.py
timemachines/skaters/drts/dartsautoarimaskater.py
timemachines/skaters/drts/dartsexpsmoothingskater.py
timemachines/skaters/drts/dartsfftskater.py
timemachines/skaters/drts/dartsfourthetaskater.py
timemachines/skaters/drts/dartsinclusion.py
timemachines/skaters/drts/dartsnbeatsskater.py
timemachines/skaters/drts/dartsprophetskater.py
timemachines/skaters/drts/dartsthetaskater.py
timemachines/skaters/drts/dartswrappers.py
timemachines/skaters/elo/__init__.py
timemachines-0.20.5.dist-info/LICENSE
timemachines-0.20.5.dist-info/METADATA
timemachines-0.20.5.dist-info/WHEEL
timemachines-0.20.5.dist-info/entry_points.txt
timemachines-0.20.5.dist-info/top_level.txt
timemachines-0.20.5.dist-info/RECORD
