Metadata-Version: 2.1
Name: timemachines
Version: 0.20.5
Summary: Evaluation and standardization of autonomous time series prediction
Home-page: https://github.com/microprediction/timemachines
Author: microprediction
Author-email: peter.cotton@microprediction.com
License: MIT
Classifier: License :: OSI Approved :: MIT License
Classifier: Programming Language :: Python :: 3
Classifier: Programming Language :: Python :: 3.7
Classifier: Programming Language :: Python :: 3.8
License-File: LICENSE
Requires-Dist: wheel
Requires-Dist: numpy (>=1.19.5)
Requires-Dist: importlib-metadata (>=1.7.0)
Requires-Dist: microconventions (>=0.5.5)
Requires-Dist: pytz
Requires-Dist: convertdate (>=2.2.0)
Requires-Dist: momentum (>=0.2.5)
Requires-Dist: requests
Provides-Extra: full
Requires-Dist: scipy ; extra == 'full'
Requires-Dist: scikit-learn ; extra == 'full'
Requires-Dist: statsmodels ; extra == 'full'
Requires-Dist: pandas ; extra == 'full'
Requires-Dist: cython ; extra == 'full'
Requires-Dist: river ; extra == 'full'
Requires-Dist: pmdarima ; extra == 'full'
Requires-Dist: sktime ; extra == 'full'
Requires-Dist: statsforecast ; extra == 'full'
